__init__.py
common/__init__.py
common/diff.py
common/dto.py
common/feed.py
common/log.py
common/offer.py
common/price.py
common/product.py
common/supplier.py
common/task.py
common/utility.py
automind_commercepro_common-1.0.9.dist-info/METADATA
automind_commercepro_common-1.0.9.dist-info/WHEEL
automind_commercepro_common-1.0.9.dist-info/top_level.txt
automind_commercepro_common-1.0.9.dist-info/RECORD
